src/main.py
garden_gateway-0.0.2.dist-info/entry_points.txt
garden_gateway-0.0.2.dist-info/LICENSE
garden_gateway-0.0.2.dist-info/WHEEL
garden_gateway-0.0.2.dist-info/METADATA
garden_gateway-0.0.2.dist-info/RECORD
